{
  "003": {
    "tipo": "VOTACIÓN",
    "fecha": "10/05/2024",
    "hora": "10:29 AM",
    "asunto": "TEXTO SUSTITUTORIO DEL PROYECTO DE LEY 7716, QUE PROPONE MODIFICAR LOS ARTÍCULOS 9 Y 72, LITERAL F), E INCORPORAR LA DÉCIMO TERCERA DISPOSICIÓN COMPLEMENTARIA TRANSITORIA EN LA LEY 30916, LEY ORGÁNICA DE LA JUNTA NACIONAL DE JUSTICIA, PARA MEJORAR SU FUNCIONAMIENTO Y SOSTENIBILIDAD"
  },
  "005": {
    "tipo": "VOTACIÓN",
    "fecha": "10/05/2024",
    "hora": "11:14 AM",
    "asunto": "TEXTO SUSTITUTORIO DE LOS PROYECTOS DE LEY 5362, 5472, 6475 Y 7388, QUE PROPONE LA LEY DE CONTRATACIONES PÚBLICAS"
  },
  "006": {
    "tipo": "VOTACIÓN",
    "fecha": "10/05/2024",
    "hora": "11:17 AM",
    "asunto": "EXONERACIÓN DE LA SEGUNDA VOTACIÓN DEL TEXTO SUSTITUTORIO DE LOS PROYECTOS DE LEY 5362, 5472, 6475 Y 7388, QUE PROPONE LA LEY DE CONTRATACIONES PÚBLICAS"
  },
  "008": {
    "tipo": "VOTACIÓN",
    "fecha": "10/05/2024",
    "hora": "11:47 AM",
    "asunto": "TEXTO SUSTITUTORIO DEL PROYECTO DE LEY 6084, QUE PROPONE OPTIMIZAR LA DEMOCRACIA REPRESENTATIVA Y ESTABLECE MEDIDAS PARA LA LUCHA CONTRA LA CORRUPCIÓN EN LAS ORGANIZACIONES POLÍTICAS"
  },
  "009": {
    "tipo": "VOTACIÓN",
    "fecha": "10/05/2024",
    "hora": "11:50 AM",
    "asunto": "EXONERACIÓN DE LA SEGUNDA VOTACIÓN DEL TEXTO SUSTITUTORIO DEL PROYECTO DE LEY 6084, QUE PROPONE OPTIMIZAR LA DEMOCRACIA REPRESENTATIVA Y ESTABLECE MEDIDAS PARA LA LUCHA CONTRA LA CORRUPCIÓN EN LAS ORGANIZACIONES POLÍTICAS"
  },
  "011": {
    "tipo": "VOTACIÓN",
    "fecha": "10/05/2024",
    "hora": "12:10 PM",
    "asunto": "TEXTO SUSTITUTORIO DE LOS PROYECTOS DE LEY 4086, 4123, 7142, 7145, 7352 Y 7353, QUE PROPONE DISPONER MEDIDAS PARA LA OPTIMIZACIÓN DEL PROCESO ELECTORAL"
  },
  "012": {
    "tipo": "VOTACIÓN",
    "fecha": "10/05/2024",
    "hora": "12:13 PM",
    "asunto": "EXONERACIÓN DE LA SEGUNDA VOTACIÓN DEL TEXTO SUSTITUTORIO DE LOS PROYECTOS DE LEY 4086, 4123, 7142, 7145, 7352 Y 7353, QUE PROPONE DISPONER MEDIDAS PARA LA OPTIMIZACIÓN DEL PROCESO ELECTORAL"
  },
  "014": {
    "tipo": "VOTACIÓN",
    "fecha": "10/05/2024",
    "hora": "12:22 PM",
    "asunto": "TEXTO SUSTITUTORIO DE LOS PROYECTOS DE LEY 10, 271, 579, 606, 613, 865, 1258, 1296 Y 1834, QUE PROPONE LA FORMALIZACIÓN, DESARROLLO Y COMPETITIVIDAD DE LA MICRO Y PEQUEÑA EMPRESA MYPE O EMPRENDIMIENTO"
  },
  "015": {
    "tipo": "VOTACIÓN",
    "fecha": "10/05/2024",
    "hora": "12:25 PM",
    "asunto": "EXONERACIÓN DE LA SEGUNDA VOTACIÓN DEL TEXTO SUSTITUTORIO DE LOS PROYECTOS DE LEY 10, 271, 579, 606, 613, 865, 1258, 1296 Y 1834, QUE PROPONE LA FORMALIZACIÓN, DESARROLLO Y COMPETITIVIDAD DE LA MICRO Y PEQUEÑA EMPRESA MYPE O EMPRENDIMIENTO"
  },
  "017": {
    "tipo": "VOTACIÓN",
    "fecha": "10/05/2024",
    "hora": "12:31 PM",
    "asunto": "RECONSIDERACIÓN DE LA VOTACIÓN DEL PROYECTO DE LEY 4086"
  },
  "019": {
    "tipo": "VOTACIÓN",
    "fecha": "10/05/2024",
    "hora": "12:40 PM",
    "asunto": "TEXTO SUSTITUTORIO DEL PROYECTO DE LEY 41, QUE PROPONE DECLARAR DE INTERÉS NACIONAL EL MEJORAMIENTO Y AMPLIACIÓN DE LOS SERVICIOS DE SALUD DEL HOSPITAL CARLOS MONGE MEDRANO DEL DISTRITO DE JULIACA, PROVINCIA DE SAN ROMÁN, DEPARTAMENTO DE PUNO"
  },
  "020": {
    "tipo": "VOTACIÓN",
    "fecha": "10/05/2024",
    "hora": "12:43 PM",
    "asunto": "EXONERACIÓN DE LA SEGUNDA VOTACIÓN DEL TEXTO SUSTITUTORIO DEL PROYECTO DE LEY 41, QUE PROPONE DECLARAR DE INTERÉS NACIONAL EL MEJORAMIENTO Y AMPLIACIÓN DE LOS SERVICIOS DE SALUD DEL HOSPITAL CARLOS MONGE MEDRANO DEL DISTRITO DE JULIACA, PROVINCIA DE SAN ROMÁN, DEPARTAMENTO DE PUNO"
  },
  "022": {
    "tipo": "VOTACIÓN",
    "fecha": "10/05/2024",
    "hora": "12:48 PM",
    "asunto": "RECONSIDERACIÓN DE LA VOTACIÓN DEL PROYECTO DE LEY 10, 271, 579, 606, 613, 865, 1258, 1296 Y 1834, QUE PROPONE LA FORMALIZACIÓN, DESARROLLO Y COMPETITIVIDAD DE LA MICRO Y PEQUEÑA EMPRESA MYPE O EMPRENDIMIENTO"
  },
  "024": {
    "tipo": "VOTACIÓN",
    "fecha": "10/05/2024",
    "hora": "12:54 PM",
    "asunto": "RECONSIDERACIÓN DE LA VOTACIÓN DE LA CUESTIÓN PREVIA DEL PROYECTO DE LEY 6589, QUE PROPONE PRECISAR LA APLICACIÓN DEL PÁRRAFO SEGUNDO DEL ARTÍCULO 84 DEL CÓDIGO PENAL, MODIFICADO POR LA LEY 31751, LEY QUE MODIFICA EL CÓDIGO PENAL Y EL NUEVO CÓDIGO PROCESAL PENAL PARA MODIFICAR LA SUSPENSIÓN DEL PLAZO DE PRESCRIPCIÓN"
  }
}