{
  "003": {
    "tipo": "VOTACIÓN",
    "fecha": "24/07/2013",
    "hora": "09:52 AM",
    "asunto": "PROPUESTA PARA DEJAR SIN EFECTO LA RESOLUCION LEGISLATIVA DEL CONGRESO 004-2012-2013-CR, QUE ELIGE A LOS MIEMBROS DEL TRIBUNAL CONSTITUCIONAL"
  },
  "005": {
    "tipo": "VOTACIÓN",
    "fecha": "24/07/2013",
    "hora": "09:59 AM",
    "asunto": "PROPUESTA PARA DEJAR SIN EFECTO LA RESOLUCIÓN LEGISLATIVA DEL CONGRESO 005-2012-2013-CR, QUE ELIGE A LA DEFENSORA DEL PUEBLO"
  },
  "007": {
    "tipo": "VOTACIÓN",
    "fecha": "24/07/2013",
    "hora": "10:04 AM",
    "asunto": "PROPUESTA PARA DEJAR SIN EFECTO LA RESOLUCIÓN LEGISLATIVA 30069, QUE ELIGIÓ A TRES MIEMBROS DEL DIRECTORIO DEL BANCO CENTRAL DE RESERVA DEL PERÚ"
  }
}