{
  "004": {
    "tipo": "VOTACIÓN",
    "fecha": "10/05/2012",
    "hora": "03:54 PM",
    "asunto": "PROY 10; MODIFICACIÓN DE LA LEY 26702, LEY GENERAL DEL SISTEMA FINANCIERO Y DEL SISTEMA DE SEGUROS Y ORGÁNICA DE LA SUPERINTENDENCIA DE BANCA, SEGUROS, CON LA FINALIDAD DE ESTABLECER MEDIDAS DE PROTECCIÓN Y SUPERVISIÓN DE LAS CONDICIONES GENERALES DE LAS PÓLIZAS DE SEGUROS MÉDICOS DE SALUD Y/O ASISTENCIA MÉDICA"
  },
  "005": {
    "tipo": "VOTACIÓN",
    "fecha": "10/05/2012",
    "hora": "03:59 PM",
    "asunto": "EXONERACIÓN DE LA SEGUNDA VOTACIÓN DEL PROY 10; MODIFICACIÓN DE LA LEY 26702, LEY GENERAL DEL SISTEMA FINANCIERO Y DEL SISTEMA DE SEGUROS Y ORGÁNICA DE LA SUPERINTENDENCIA DE BANCA, SEGUROS, CON LA FINALIDAD DE ESTABLECER MEDIDAS DE PROTECCIÓN Y SUPERVISIÓN DE LAS CONDICIONES GENERALES DE LAS PÓLIZAS DE SEGUROS"
  },
  "007": {
    "tipo": "VOTACIÓN",
    "fecha": "10/05/2012",
    "hora": "05:21 PM",
    "asunto": "PROY 23; LEY QUE PRIORIZA LA ASIGNACIÓN PROGRESIVA DE PLAZAS DOCENTES DE EDUCACIÓN FÍSICA EN EL NIVEL PRIMARIA"
  },
  "008": {
    "tipo": "VOTACIÓN",
    "fecha": "10/05/2012",
    "hora": "05:25 PM",
    "asunto": "EXONERACIÓN DE LA SEGUNDA VOTACIÓN DEL PROY 23; LEY QUE PRIORIZA LA ASIGNACIÓN PROGRESIVA DE PLAZAS DOCENTES DE EDUCACIÓN FÍSICA EN EL NIVEL PRIMARIO"
  },
  "010": {
    "tipo": "VOTACIÓN",
    "fecha": "10/05/2012",
    "hora": "05:54 PM",
    "asunto": "PROY 164; LEY QUE FACILITA EL PAGO Y LA RECONEXION DE LOS SERVICIOS PUBLICOS DE AGUA, ELECTRICIDAD, GAS NATURAL Y TELEFONÍA"
  },
  "011": {
    "tipo": "VOTACIÓN",
    "fecha": "10/05/2012",
    "hora": "05:57 PM",
    "asunto": "EXONERACIÓN DE LA SEGUNDA VOTACIÓN DEL PROY 164; LEY QUE FACILITA EL PAGO Y LA RECONEXIÓN DE LOS SERVICIOS PÚBLICOS DE AGUA, ELECTRICIDAD, GAS NATURAL Y TELEFONÍA"
  },
  "013": {
    "tipo": "VOTACION",
    "fecha": "10/05/2012",
    "hora": "06:15 PM",
    "asunto": "PROYS 421, 647, 757, 1054 Y 1055; LEY QUE IMPLEMENTA MEDIDAS DESTINADAS A FIJAR UNA ESCALA BASE PARA EL INCENTIVO LABORAL QUE SE OTORGA A TRAVÉS DEL CAFAE"
  },
  "014": {
    "tipo": "VOTACIÓN",
    "fecha": "10/05/2012",
    "hora": "06:19 PM",
    "asunto": "EXONERACIÓN DE LA SEGUNDA VOTACIÓN DE LOS PROYS 421, 647, 757, 1054 Y 1055; LEY QUE IMPLEMENTA MEDIDAS DESTINADAS A FIJAR UNA ESCALA BASE PARA EL INCENTIVO LABORAL QUE SE OTORGA A TRAVÉS DEL CAFAE"
  },
  "016": {
    "tipo": "VOTACIÓN",
    "fecha": "10/05/2012",
    "hora": "06:50 PM",
    "asunto": "PROY 689; MODIFICACIÓN DE LA LEY 28951, LEY DE ACTUALIZACIÓN PROFESIONAL DEL CONTADOR PÚBLICO"
  },
  "017": {
    "tipo": "VOTACIÓN",
    "fecha": "10/05/2012",
    "hora": "06:53 PM",
    "asunto": "EXONERACIÓN DE LA SEGUNDA VOTACIÓN DEL PROY 689; MODIFICACIÓN DE LA LEY 28951, LEY DE ACTUALIZACIÓN PROFESIONAL DEL CONTADOR PÚBLICO"
  },
  "019": {
    "tipo": "VOTACIÓN",
    "fecha": "10/05/2012",
    "hora": "08:04 PM",
    "asunto": "CUESTION PREVIA PARA DAR POR AGOTADO EL DEBATE DEL PROY 1093; LEY DE DEMARCACIÓN Y ORGANIZACIÓN TERRITORIAL DE LA PROVINCIA ALTO AMAZONAS EN EL DEPARTAMENTO DE LORETO"
  },
  "020": {
    "tipo": "VOTACION",
    "fecha": "10/05/2012",
    "hora": "08:09 PM",
    "asunto": "PROY 1093; LEY DE DEMARCACIÓN Y ORGANIZACIÓN TERRITORIAL DE LA PROVINCIA ALTO AMAZONAS EN EL DEPARTAMENTO DE LORETO; Y AUTORIZACIÓN A LA MESA DIRECTIVA DE LA COMISIÓN DE DECENTRALIZACIÓN PARA CONSTITUIRSE COMO COMISIÓN REDACTORA"
  },
  "022": {
    "tipo": "VOTACIÓN",
    "fecha": "10/05/2012",
    "hora": "08:21 PM",
    "asunto": "RESOLUCIÓN LEGISLATIVA 1103; QUE AUTORIZA EL INGRESO DE LA UNIDAD NAVAL DE MÉXICO PARA EL EJERCICIO MULTINACIONAL UNITAS 2012"
  },
  "024": {
    "tipo": "VOTACIÓN",
    "fecha": "10/05/2012",
    "hora": "08:27 PM",
    "asunto": "ACLARACIÓN AL TEXTO SUSTITUTORIO APROBADO DEL PROY 689; LEY QUE MODIFICA Y AMPLÍA LA SEGUNDA DISPOSICIÓN COMPLEMENTARIA, TRANSITORIA Y FINAL DE LA LEY 28951, LEY DE ACTUALIZACIÓN PROFESIONAL DEL CONTADOR PÚBLICO"
  }
}