{
  "003": {
    "tipo": "VOTACIÓN",
    "fecha": "08/03/2012",
    "hora": "11:20 AM",
    "asunto": "CONSULTA AL PLENO PARA DAR POR AGOTADO EL DEBATE Y PASAR A LA AGENDA DEL PLENO"
  },
  "005": {
    "tipo": "VOTACIÓN",
    "fecha": "08/03/2012",
    "hora": "12:19 PM",
    "asunto": "LEVANTAMIENTO DE LA INMUNIDAD PARLAMENTARIA DE LA CONGRESISTA MARÍA MAGDALENA LÓPEZ CÓRDOVA"
  },
  "007": {
    "tipo": "VOTACIÓN",
    "fecha": "08/03/2012",
    "hora": "12:28 PM",
    "asunto": "LEVANTAMIENTO DE LA INMUNIDAD PARLAMENTARIA DEL CONGRESISTA EULOGIO AMADO ROMERO RODRÍGUEZ"
  },
  "009": {
    "tipo": "VOTACIÓN",
    "fecha": "08/03/2012",
    "hora": "12:43 PM",
    "asunto": "PROYECTO DE RESOLUCIÓN LEGISLATIVA 269; QUE PROPONE APROBAR EL TRATADO DE EXTRADICIÓN ENTRE LA REPÚBLICA DEL PERÚ Y LA REPÚBLICA ORIENTAL DEL URUGUAY"
  },
  "011": {
    "tipo": "VOTACIÓN",
    "fecha": "08/03/2012",
    "hora": "12:55 PM",
    "asunto": "PROYECTO DE RESOLUCIÓN LEGISLATIVA 271; QUE PROPONE APROBAR EL CONVENIO SOBRE TRASLADO DE PERSONAS CONDENADAS ENTRE LA REPÚBLICA DEL PERÚ Y SUIZA"
  },
  "013": {
    "tipo": "VOTACIÓN",
    "fecha": "08/03/2012",
    "hora": "01:14 PM",
    "asunto": "PROYECTO DE RESOLUCIÓN LEGISLATIVA 386; QUE PROPONE APROBAR LA CONVENCIÓN SOBRE MUNICIONES EN RACIMO"
  },
  "015": {
    "tipo": "VOTACIÓN",
    "fecha": "08/03/2012",
    "hora": "01:30 PM",
    "asunto": "PROYECTO DE RESOLUCIÓN LEGISLATIVA 387; QUE PROPONE APROBAR EL ACUERDO DE ASISTENCIA JURÍDICA MUTUA EN ASUNTOS PENALES ENTRE LOS ESTADOS PARTES DEL MERCOSUR, LA REPÚBLICA DE BOLIVIA Y LA REPÚBLICA DE CHILE"
  }
}