{
  "003": {
    "tipo": "VOTACIÓN",
    "fecha": "20/05/2021",
    "hora": "10:41 AM",
    "asunto": "CUESTIÓN PREVIA PARA QUE RETORNE A LA COMISIÓN DE CIENCIA Y TECNOLOGÍA Y PASE A LA COMISIÓN DE TRABAJO, EL PROYECTO DE LEY 5408, QUE PROPONE LA LEY DEL TELETRABAJO"
  },
  "004": {
    "tipo": "VOTACIÓN",
    "fecha": "20/05/2021",
    "hora": "12:18 PM",
    "asunto": "TEXTO SUSTITUTORIO DE LOS PROYECTOS DE LEY 5862 Y 6437, QUE PROPONE LA LEY QUE DECLARA DE INTERÉS NACIONAL Y NECESIDAD PÚBLICA LA CREACIÓN DEL DISTRITO DE SAN JUAN DE QUISPILLACCTA"
  },
  "005": {
    "tipo": "VOTACIÓN",
    "fecha": "20/05/2021",
    "hora": "12:23 PM",
    "asunto": "EXONERACIÓN DE LA SEGUNDA VOTACIÓN DEL TEXTO SUSTITUTORIO DE LOS PROYECTOS DE LEY 5862 Y 6437, QUE PROPONE LA LEY QUE DECLARA DE INTERÉS NACIONAL Y NECESIDAD PÚBLICA LA CREACIÓN DEL DISTRITO DE SAN JUAN DE QUISPILLACCTA"
  },
  "007": {
    "tipo": "VOTACIÓN",
    "fecha": "20/05/2021",
    "hora": "12:47 PM",
    "asunto": "TEXTO SUSTITUTORIO DE LOS PROYECTOS DE LEY 3621 Y 6088, QUE PROPONE LA LEY QUE INSTITUCIONALIZA EL 30 DE JUNIO DE CADA AÑO COMO EL DÍA DEL INGENIERO AGRÓNOMO EN EL PERÚ"
  },
  "008": {
    "tipo": "VOTACIÓN",
    "fecha": "20/05/2021",
    "hora": "12:52 PM",
    "asunto": "EXONERACIÓN DE LA SEGUNDA VOTACIÓN DEL TEXTO SUSTITUTORIO DE LOS PROYECTOS DE LEY 3621 Y 6088, QUE PROPONE LA LEY QUE INSTITUCIONALIZA EL 30 DE JUNIO DE CADA AÑO COMO EL DÍA DEL INGENIERO AGRÓNOMO EN EL PERÚ"
  },
  "010": {
    "tipo": "VOTACIÓN",
    "fecha": "20/05/2021",
    "hora": "01:48 PM",
    "asunto": "PROYECTO DE LEY 7695 (ACTUALIZADO), QUE PROPONE LA LEY DE CREACIÓN DEL DISTRITO DE HUAYCÁN EN LA PROVINCIA Y DEPARTAMENTO DE LIMA"
  },
  "011": {
    "tipo": "VOTACIÓN",
    "fecha": "20/05/2021",
    "hora": "01:51 PM",
    "asunto": "EXONERACIÓN DE LA SEGUNDA VOTACIÓN DEL PROYECTO DE LEY 7695 (ACTUALIZADO), QUE PROPONE LA LEY DE CREACIÓN DEL DISTRITO DE HUAYCÁN EN LA PROVINCIA Y DEPARTAMENTO DE LIMA"
  },
  "012": {
    "tipo": "VOTACIÓN",
    "fecha": "20/05/2021",
    "hora": "02:08 PM",
    "asunto": "TEXTO SUSTITUTORIO DEL PROYECTO DE LEY 5884, QUE PROPONE LA LEY QUE DECLARA DE INTERÉS NACIONAL Y NECESIDAD PÚBLICA LA CREACIÓN DEL DISTRITO DE RANCHA"
  },
  "013": {
    "tipo": "VOTACIÓN",
    "fecha": "20/05/2021",
    "hora": "02:12 PM",
    "asunto": "EXONERACIÓN DE LA SEGUNDA VOTACIÓN DEL TEXTO SUSTITUTORIO DEL PROYECTO DE LEY 5884, QUE PROPONE LA LEY QUE DECLARA DE INTERÉS NACIONAL Y NECESIDAD PÚBLICA LA CREACIÓN DEL DISTRITO DE RANCHA"
  },
  "015": {
    "tipo": "VOTACIÓN",
    "fecha": "20/05/2021",
    "hora": "04:21 PM",
    "asunto": "TEXTO SUSTITUTORIO DE LOS PROYECTOS DE LEY 2206, 3964, 4359, 5261, 5368, 5475, 5631, 6333 Y 6389, QUE PROPONE LA LEY DEL REGISTRO MILITAR, SERVICIO MILITAR Y RESERVAS PARA LA MOVILIZACIÓN DE RECURSOS HUMANOS"
  },
  "016": {
    "tipo": "VOTACIÓN",
    "fecha": "20/05/2021",
    "hora": "04:25 PM",
    "asunto": "EXONERACIÓN DE LA SEGUNDA VOTACIÓN DEL TEXTO SUSTITORIO DE LOS PROYECTOS DE LEY 2206, 3964, 4359, 5261, 5368, 5475, 5631, 6333 Y 6389, QUE PROPONE LA LEY DEL REGISTRO MILITAR, SERVICIO MILITAR Y RESERVAS PARA LA MOVILIZACIÓN DE RECURSOS HUMANOS"
  },
  "018": {
    "tipo": "VOTACIÓN",
    "fecha": "20/05/2021",
    "hora": "05:10 PM",
    "asunto": "TEXTO SUSTITUTORIO DEL PROYECTO DE LEY 4090, QUE PROPONE LA LEY DEL EJERCICIO PROFESIONAL DEL NUTRICIONISTA"
  },
  "019": {
    "tipo": "VOTACIÓN",
    "fecha": "20/05/2021",
    "hora": "05:14 PM",
    "asunto": "EXONERACIÓN DE LA SEGUNDA VOTACIÓN DEL TEXTO SUSTITUTORIO DEL PROYECTO DE LEY 4090, QUE PROPONE LA LEY DEL EJERCICIO PROFESIONAL DEL NUTRICIONISTA"
  },
  "020": {
    "tipo": "VOTACIÓN",
    "fecha": "20/05/2021",
    "hora": "05:23 PM",
    "asunto": "CUESTIÓN PREVIA PARA QUE RETORNEN A LA COMISIÓN DE JUSTICIA, LOS PROYECTOS DE LEY 1017, 2705 Y 2950, QUE PROPONEN LA LEY QUE MODIFICA EL DECRETO LEGISLATIVO 1322, DECRETO LEGISLATIVO QUE REGULA LA VIGILANCIA ELECTRÓNICA PERSONAL Y SE CREA LA COMISIÓN ESPECIAL DE DESHACINAMIENTO DE LOS ESTABLECIMIENTOS PENITENCIARIOS DE LIMA Y CALLAO"
  },
  "021": {
    "tipo": "VOTACIÓN",
    "fecha": "20/05/2021",
    "hora": "06:27 PM",
    "asunto": "CUESTIÓN PREVIA PARA QUE RETORNE A LA COMISIÓN DE PUEBLOS ANDINOS Y DE CONSTITUCIÓN Y PASE A LA COMISIÓN DE JUSTICIA, EL PROYECTO DE LEY 6699, QUE PROPONE LA LEY DE RECONOCIMIENTO PLENO Y REGISTRO DE LA PERSONALIDAD JURÍDICA DE PUEBLOS INDÍGENAS U ORIGINARIOS, Y PUEBLOS AFROPERUANOS"
  },
  "023": {
    "tipo": "VOTACIÓN",
    "fecha": "20/05/2021",
    "hora": "06:48 PM",
    "asunto": "TEXTO SUSTITUTORIO CONSENSUADO DE LOS PROYECTOS DE LEY DE 2507, 3691, 4122, 6233 Y 7636, QUE PROPONE LA LEY QUE REGULA EL SANEAMIENTO FÍSICO-LEGAL DE LOS BIENES INMUEBLES DEL SECTOR EDUCACIÓN DESTINADOS A INSTITUCIONES EDUCATIVAS PÚBLICAS"
  },
  "024": {
    "tipo": "VOTACIÓN",
    "fecha": "20/05/2021",
    "hora": "06:52 PM",
    "asunto": "EXONERACIÓN DE LA SEGUNDA VOTACIÓN DEL TEXTO SUSTITUTORIO CONSENSUADO DE LOS PROYECTOS DE LEY DE 2507, 3691, 4122, 6233 Y 7636, QUE PROPONE LA LEY QUE REGULA EL SANEAMIENTO FÍSICO-LEGAL DE LOS BIENES INMUEBLES DEL SECTOR EDUCACIÓN DESTINADOS A INSTITUCIONES EDUCATIVAS PÚBLICAS"
  },
  "026": {
    "tipo": "VOTACIÓN",
    "fecha": "20/05/2021",
    "hora": "07:04 PM",
    "asunto": "INSISTENCIA EN LA AUTÓGRAFA OBSERVADA POR EL SEÑOR PRESIDENTE DE LA REPÚBLICA RECAÍDA EN LOS PROYECTOS DE LEY 5398, 5942, 6283 Y 6445, QUE PROPONE LA LEY QUE GARANTIZA LA VELOCIDAD MÍNIMA DE CONEXIÓN A INTERNET Y MONITOREO DE LA PRESTACIÓN DEL SERVICIO DE INTERNET A FAVOR DE LOS USUARIOS"
  },
  "028": {
    "tipo": "VOTACIÓN",
    "fecha": "20/05/2021",
    "hora": "08:29 PM",
    "asunto": "TEXTO SUSTITUTORIO DEL PROYECTO DE LEY 6583, QUE PROPONE LA LEY QUE DECLARA DE NECESIDAD PÚBLICA E INTERÉS NACIONAL LA CONSTRUCCIÓN Y MEJORAMIENTO DE LA CARRETERA DEL TRAMO PASCO - HUACHÓN - HUANCABAMBA - OXAPAMPA, EN EL DEPARTAMENTO DE PASCO"
  },
  "029": {
    "tipo": "VOTACIÓN",
    "fecha": "20/05/2021",
    "hora": "08:33 PM",
    "asunto": "EXONERACIÓN DE LA SEGUNDA VOTACIÓN DEL TEXTO SUSTITUTORIO DEL PROYECTO DE LEY 6583, QUE PROPONE LA LEY QUE DECLARA DE NECESIDAD PÚBLICA E INTERÉS NACIONAL LA CONSTRUCCIÓN Y MEJORAMIENTO DE LA CARRETERA DEL TRAMO PASCO - HUACHÓN - HUANCABAMBA - OXAPAMPA, EN EL DEPARTAMENTO DE PASCO"
  },
  "030": {
    "tipo": "VOTACIÓN",
    "fecha": "20/05/2021",
    "hora": "08:57 PM",
    "asunto": "TEXTO SUSTITUTORIO DEL PROYECTO DE LEY 5866, QUE PROPONE LA LEY QUE DECLARA DE INTERÉS NACIONAL Y NECESIDAD PÚBLICA LA CONSTRUCCIÓN E IMPLEMENTACIÓN DE UN NUEVO HOSPITAL CON CATEGORÍA III-1 EN LA CIUDAD DE AREQUIPA"
  },
  "031": {
    "tipo": "VOTACIÓN",
    "fecha": "20/05/2021",
    "hora": "09:02 PM",
    "asunto": "EXONERACIÓN DE LA SEGUNDA VOTACIÓN DEL TEXTO SUSTITUTORIO DEL PROYECTO DE LEY 5866, QUE PROPONE LA LEY QUE DECLARA DE INTERÉS NACIONAL Y NECESIDAD PÚBLICA LA CONSTRUCCIÓN E IMPLEMENTACIÓN DE UN NUEVO HOSPITAL CON CATEGORÍA III-1 EN LA CIUDAD DE AREQUIPA"
  },
  "033": {
    "tipo": "VOTACIÓN",
    "fecha": "20/05/2021",
    "hora": "09:13 PM",
    "asunto": "TEXTO SUSTITUTORIO DEL PROYECTO DE LEY 6515, QUE PROPONE LA LEY QUE DECLARA DE INTERÉS NACIONAL Y NECESIDAD PÚBLICA LA CREACIÓN DEL DISTRITO DE HUAYANAY"
  },
  "034": {
    "tipo": "VOTACIÓN",
    "fecha": "20/05/2021",
    "hora": "09:17 PM",
    "asunto": "EXONERACIÓN DE LA SEGUNDA VOTACIÓN DEL TEXTO SUSTITUTORIO DEL PROYECTO DE LEY 6515, QUE PROPONE LA LEY QUE DECLARA DE INTERÉS NACIONAL Y NECESIDAD PÚBLICA LA CREACIÓN DEL DISTRITO DE HUAYANAY"
  }
}