{
  "003": {
    "tipo": "VOTACIÓN",
    "fecha": "13/12/2012",
    "hora": "05:24 PM",
    "asunto": "CUESTIÓN PREVIA PARA VOTAR POR SEPARADO EL NUMERAL 2.2 DEL ARTÍCULO 2 DE LOS PROYS. 1396 Y 1794; LEY QUE AFIANZA LA SEGURIDAD ENERGÉTICA Y PROMUEVE EL DESARROLLO DE POLO PETROQUÍMICO EN EL SUR DEL PAÍS"
  },
  "005": {
    "tipo": "VOTACIÓN",
    "fecha": "13/12/2012",
    "hora": "05:32 PM",
    "asunto": "PROYS. 1396 Y 1794; LEY QUE AFIANZA LA SEGURIDAD ENERGÉTICA Y PROMUEVE EL DESARROLLO DE POLO PETROQUÍMICO EN EL SUR DEL PAÍS"
  },
  "006": {
    "tipo": "VOTACIÓN",
    "fecha": "13/12/2012",
    "hora": "05:35 PM",
    "asunto": "EXONERACIÓN DE LA SEGUNDA VOTACIÓN DE LOS PROYS. 1396 Y 1794; LEY QUE AFIANZA LA SEGURIDAD ENERGÉTICA Y PROMUEVE EL DESARROLLO DE POLO PETROQUÍMICO EN EL SUR DEL PAÍS"
  },
  "008": {
    "tipo": "VOTACION",
    "fecha": "13/12/2012",
    "hora": "05:52 PM",
    "asunto": "PROY. 1814; LEY QUE AMPLIA LOS ALCANCES DEL ARTÍCULO 20 DE LA LEY 29951, LEY DE PRESUPUESTO DEL SECTOR PÚBLICO PARA EL AÑO FISCAL 2013 Y DICTA OTRAS DISPOSICIONES, REFERNE A LOS MEDICAMENTOS"
  },
  "010": {
    "tipo": "VOTACIÓN",
    "fecha": "13/12/2012",
    "hora": "06:04 PM",
    "asunto": "CUESTIÓN PREVIA PARA VOTAR POR SEPARADO LA DISPOSICIÓN COMPLEMENTARIA FINAL PRIMERA DEL PROY. 1757; LEY QUE PRORROGA LA VIGENCIA DEL PLAZO ESTABLECIDO EN EL LITERAL C) DEL ARTÍCULO 14 DEL DECRETO LEGISLATIVO 709, LEY DE PROMOCIÓN A LA INVERSIÓN PRIVADA EN PREDIOS PARA ARRENDAMIENTO"
  },
  "011": {
    "tipo": "VOTACION",
    "fecha": "13/12/2012",
    "hora": "06:07 PM",
    "asunto": "PROY. 1757; LEY QUE PRORROGA LA VIGENCIA DEL PLAZO ESTABLECIDO EN EL LITERAL C) DEL ARTICULO 14 DEL DECRETO LEGISLATIVO 709, LEY DE PROMOCION A LA INVERSION PRIVADA EN PREDIOS PARA ARRENDAMIENTO (EXCEPTO LA DISPOSICION COMPLEMENTARIA FINAL PRIMERA)"
  },
  "012": {
    "tipo": "VOTACIÓN",
    "fecha": "13/12/2012",
    "hora": "06:10 PM",
    "asunto": "EXONERACIÓN DE LA SEGUNDA VOTACIÓN DEL PROY. 1757; LEY QUE PRORROGA LA VIGENCIA DEL PLAZO ESTABLECIDO EN EL LITERAL C) DEL ARTÍCULO 14 DEL DECRETO LEGISLATIVO 709, LEY DE PROMOCIÓN A LA INVERSIÓN PRIVADA EN PREDIOS PARA ARRENDAMIENTO"
  },
  "014": {
    "tipo": "VOTACIÓN",
    "fecha": "13/12/2012",
    "hora": "07:35 PM",
    "asunto": "PROYS. 436, 1018, 1205, 1341, 1427 Y 1496: LEY QUE REGULA MEDIDAS EXTRAORDINARIAS PARA EL PERSONAL DOCENTE O ADMINISTRATIVO IMPLICADO EN DELITOS DE APOLOGÍA DE TERRORISMO, TERRORISMO O SUS FORMAS AGRAVADAS"
  },
  "015": {
    "tipo": "VOTACIÓN",
    "fecha": "13/12/2012",
    "hora": "07:38 PM",
    "asunto": "EXONERACIÓN DE LA SEGUNDA VOTACIÓN DE LOS PROYS. 436, 1018, 1205, 1341, 1427 Y 1496; LEY QUE REGULA MEDIDAS EXTRAORDINARIAS PARA EL PERSONAL DOCENTE O ADMINISTRATIVO IMPLICADO EN DELITOS DE APOLOGÍA DE TERRORISMO, TERRORISMO O SUS FORMAS AGRAVADAS"
  },
  "017": {
    "tipo": "VOTACIÓN",
    "fecha": "13/12/2012",
    "hora": "07:53 PM",
    "asunto": "ACLARACIÓN SOBRE ARTÍCULO 2 DEL PROY. 945; LEY QUE MODIFICA EL ARTÍCULO 239 DEL CODIGO PROCESAL PENAL APROBADO POR EL DECRETO LEGISLATIVO 638 Y EL ARTÍCULO 195 DEL NUEVO CODIGO PROCESAL PENAL APROBADO POR EL DECRETO LEGISLATIVO 957 - APROBADO EL 06 DE DICIEMBRE DEL 2012"
  },
  "019": {
    "tipo": "VOTACIÓN",
    "fecha": "13/12/2012",
    "hora": "08:13 PM",
    "asunto": "CUESTIÓN PREVIA PARA QUE VUELVA A LA COMISIÓN DE VIVIENDA EL PROY. 482; LEY QUE REGULA LA EJECUCIÓN DE OBRAS DE SERVICIOS PÚBLICOS AUTORIZADAS POR LAS MUNICIPALIDADES EN LAS ÁREAS DE DOMINIO PÚBLICO"
  },
  "021": {
    "tipo": "VOTACIÓN",
    "fecha": "13/12/2012",
    "hora": "10:47 PM",
    "asunto": "TEXTO SUSTITUTORIO DE LOS PROYS. 235, 316, 322, 487, 577, 606, 645, 679, 807, 816, 830, 998, 1133, 1146, 1236, 1510, 1538, 1612, 1658 Y 1696; LEY QUE ESTABLECE LA MORATORIA DE CREACIÓN DE UNIVERSIDADES PÚBLICAS Y PRIVADAS POR UN PERÍODO DE CINCO AÑOS"
  },
  "022": {
    "tipo": "VOTACIÓN",
    "fecha": "13/12/2012",
    "hora": "10:50 PM",
    "asunto": "EXONERACIÓN DE LA SEGUNDA VOTACIÓN DE LOS PROYS. 235, 316, 322, 487, 577, 606, 645, 679, 807, 816, 830, 998, 1133, 1146, 1236, 1510, 1538, 1612, 1658 Y 1696; LEY QUE ESTABLECE LA MORATORIA DE CREACIÓN DE UNIVERSIDADES PÚBLICAS Y PRIVADAS POR UN PERÍODO DE CINCO AÑOS"
  },
  "024": {
    "tipo": "VOTACIÓN",
    "fecha": "13/12/2012",
    "hora": "10:57 PM",
    "asunto": "RECONSIDERACIÓN A LA VOTACIÓN DEL TEXTO SUSTITUTORIO DE LOS PROYS. 235, 316, 322, 487, 577, 606, 645, 679, 807, 816, 830, 998, 1133, 1146, 1236, 1510, 1538, 1612, 1658 Y 1696; LEY QUE ESTABLECE LA MORATORIA DE CREACIÓN DE UNIVERSIDADES PÚBLICAS Y PRIVADAS POR UN PERÍODO DE CINCO AÑOS"
  },
  "026": {
    "tipo": "VOTACIÓN",
    "fecha": "13/12/2012",
    "hora": "11:04 PM",
    "asunto": "RESOLUCIÓN LEGISLATIVA DEL CONGRESO MEDIANTE LA CUAL SE DELEGA EN LA COMISIÓN PERMANENTE LA FACULTAD DE LEGISLAR DEL 17 DE DICIEMBRE DE 2012 AL 28 DE FEBRERO DE 2013"
  },
  "028": {
    "tipo": "VOTACIÓN",
    "fecha": "13/12/2012",
    "hora": "11:10 PM",
    "asunto": "SEGUNDA VOTACIÓN DE LOS PROYS. 589, 620, 1353 Y 1643; LEY DE DEMARCACIÓN Y ORGANIZACIÓN TERRITORIAL DE LA PROVINCIA DE PIURA EN EL DEPARTAMENTO DE PIURA"
  },
  "030": {
    "tipo": "VOTACION",
    "fecha": "13/12/2012",
    "hora": "11:23 PM",
    "asunto": "TEXTO SUSTITUTORIO DEL PROY. 870; LEY QUE DECLARA DE INTERÉS NACIONAL LA PROMOCIÓN DE LA CIENCIA, LA INNOVACIÓN Y LA TECNOLOGÍA A TRAVÉS DE LAS ASOCIACIONES PÚBLICO - PRIVADAS"
  },
  "031": {
    "tipo": "VOTACIÓN",
    "fecha": "13/12/2012",
    "hora": "11:26 PM",
    "asunto": "EXONERACIÓN DE LA SEGUNDA VOTACIÓN DEL TEXTO SUSTITUTORIO DEL PROY. 870; LEY QUE DECLARA DE INTERÉS NACIONAL LA PROMOCIÓN DE LA CIENCIA, LA INNOVACIÓN Y LA TECNOLOGÍA A TRAVÉS DE LAS ASOCIACIONES PÚBLICO - PRIVADAS"
  },
  "033": {
    "tipo": "VOTACIÓN",
    "fecha": "13/12/2012",
    "hora": "11:46 PM",
    "asunto": "CUESTIÓN PREVIA PARA QUE VUELVA A LA COMISIÓN DE VIVIENDA EL PROY. 1761; LEY QUE AMPLIA EL PLAZO DE VIGENCIA DE LA LEY 29650, LEY QUE DECLARA DE NECESIDAD PÚBLICA LA OBRA RESTAURACIÓN Y REHABILITACIÓN DEL ENTORNO DE LA PLAZA DE ACHO, ASÍ COMO LA EXPROPIACIÓN DE INMUEBLES PARA SU EJECUCIÓN"
  },
  "035": {
    "tipo": "VOTACIÓN",
    "fecha": "14/12/2012",
    "hora": "00:27 AM",
    "asunto": "ACUERDO DE LA COMISIÓN DE LEVANTAMIENTO DE INMUNIDAD PARLAMENTARIA, MEDIANTE EL CUAL CONCLUYE DESESTIMAR Y DECLARAR IMPROCEDENTE, RESPECTO DEL PEDIDO DE LA CORTE SUPREMA DE JUSTICIA PARA QUE SE LEVANTE LA INMUNIDAD PARLAMENTARIA AL CONGRESISTA EULOGIO AMADO ROMERO RODRÍGUEZ"
  },
  "037": {
    "tipo": "VOTACIÓN",
    "fecha": "14/12/2012",
    "hora": "00:59 AM",
    "asunto": "INFORME PRELIMINAR DE LA COMISIÓN DE FISCALIZACIÓN Y CONTRALORÍA, CON CARACTER DE INVESTIGADORA SOBRE LAS PRESUNTAS IRREGULARIDADES QUE HABÍAN SUCEDIDO EN LA GESTIÓN DEL ALCALDE DE ICA, POR EL QUE SOLICITA UNA PRÓRROGA DE PLAZO DE 180 DÍAS CALENDARIOS"
  },
  "039": {
    "tipo": "VOTACIÓN",
    "fecha": "14/12/2012",
    "hora": "01:04 AM",
    "asunto": "SEGUNDA VOTACIÓN DEL PROY. 1356; LEY QUE ESTABLECE CRITERIOS DE PRIORIZACIÓN PARA LA EJECUCIÓN DEL PROGRAMA DE REPARACIÓN ECONÓMICA DEL PLAN INTEGRAL DE REPARACIONES (PIR), CREADO POR LA LEY 28592, LEY QUE CREA EL PLAN INTEGRAL DE REPARACIONES"
  },
  "041": {
    "tipo": "VOTACIÓN",
    "fecha": "14/12/2012",
    "hora": "02:42 AM",
    "asunto": "CUESTIÓN PREVIA PARA POSTERGAR EL DEBATE DEL PROY. 1816 EN LA COMISIÓN PERMANENTE."
  },
  "042": {
    "tipo": "VOTACIÓN",
    "fecha": "14/12/2012",
    "hora": "02:44 AM",
    "asunto": "CUESTIÓN PREVIA PARA QUE PASE A LAS COMISIONES DE ECONOMÍA Y AGRARIA EL PROY. 1816; LEY QUE REGULA EL MARCO NORMATIVO PARA PROMOVER LA INCLUSIÓN DE LOS PRODUCTORES AGRARIOS A TRAVÉS DE LAS COOPERATIVAS, MEJORANDO SU CAPACIDAD DE NEGOCIACIÓN Y GENERANDO ECONOMÍAS DE ESCALA, PERMITIÉNDOLES INSERTARSE"
  },
  "044": {
    "tipo": "VOTACIÓN",
    "fecha": "14/12/2012",
    "hora": "03:04 AM",
    "asunto": "PROY. 1050; LEY QUE DECLARA DE INTERÉS NACIONAL Y NECESIDAD PÚBLICA LA ADQUISICIÓN DE UNA DRAGA PARA ENFRENTAR LA EROSIÓN EN EL LITORAL PERUANO (AUTÓGRAFA OBSERVADA POR EL PODER EJECUTIVO)"
  },
  "045": {
    "tipo": "VOTACIÓN",
    "fecha": "14/12/2012",
    "hora": "03:06 AM",
    "asunto": "EXONERACIÓN DE LA SEGUNDA VOTACIÓN DEL PROY. 1050; LEY QUE DECLARA DE INTERÉS NACIONAL Y NECESIDAD PÚBLICA LA ADQUISICIÓN DE UNA DRAGA PARA ENFRENTAR LA EROSIÓN EN EL LITORAL PERUANO (AUTÓGRAFA OBSERVADA POR EL PODER EJECUTIVO)"
  },
  "047": {
    "tipo": "VOTACIÓN",
    "fecha": "14/12/2012",
    "hora": "03:11 AM",
    "asunto": "PROY. 1816; LEY QUE REGULA EL MARCO NORMATIVO PARA PROMOVER LA INCLUSIÓN DE LOS PRODUCTORES AGRARIOS A TRAVÉS DE LAS COOPERATIVAS, MEJORANDO SU CAPACIDAD DE NEGOCIACIÓN Y GENERANDO ECONOMÍAS DE ESCALA, PERMITIÉNDOLES INSERTARSE COMPETITIVAMENTE EN EL MERCADO"
  },
  "048": {
    "tipo": "VOTACIÓN",
    "fecha": "14/12/2012",
    "hora": "03:13 AM",
    "asunto": "EXONERACIÓN DE LA SEGUNDA VOTACIÓN DEL PROY. 1816; LEY QUE REGULA EL MARCO NORMATIVO PARA PROMOVER LA INCLUSIÓN DE LOS PRODUCTORES AGRARIOS A TRAVÉS DE LAS COOPERATIVAS, MEJORANDO SU CAPACIDAD DE NEGOCIACIÓN Y GENERANDO ECONOMÍAS DE ESCALA, PERMITIÉNDOLES INSERTARSE COMPETITIVAMENTE EN EL MERCADO"
  }
}