{
  "003": {
    "tipo": "VOTACIÓN",
    "fecha": "5/09/2022",
    "hora": "07:18 PM",
    "asunto": "ADMISIÓN A DEBATE DE LA MOCIÓN 3833, QUE PROPONE QUE EL CONGRESO DE LA REPÚBLICA CENSURE A LA PRESIDENTE DEL CONGRESO DE LA REPÚBLICA, LADY MERCEDES CAMONES SORIANO, POR LOS FUNDAMENTOS EXPUESTOS EN LA PARTE CONSIDERATIVA Y POR ATENTAR CONTRA LA CONSTITUCIÓN POLÍTICA DEL PERÚ EN SUS ARTÍCULOS 43 Y 45, Y A LOS PRINCIPIOS RECTORES QUE CARACTERIZAN A NUESTRA DEMOCRACIA Y AL ORDEN CONSTITUCIONAL"
  },
  "005": {
    "tipo": "VOTACIÓN",
    "fecha": "5/09/2022",
    "hora": "08:05 PM",
    "asunto": "MOCIÓN 3833, QUE PROPONE QUE EL CONGRESO DE LA REPÚBLICA CENSURE A LA PRESIDENTE DEL CONGRESO DE LA REPÚBLICA, LADY MERCEDES CAMONES SORIANO, POR LOS FUNDAMENTOS EXPUESTOS EN LA PARTE CONSIDERATIVA Y POR ATENTAR CONTRA LA CONSTITUCIÓN POLÍTICA DEL PERÚ EN SUS ARTÍCULOS 43 Y 45, Y A LOS PRINCIPIOS RECTORES QUE CARACTERIZAN A NUESTRA DEMOCRACIA Y AL ORDEN CONSTITUCIONAL"
  }
}