{
  "003": {
    "tipo": "VOTACIÓN",
    "fecha": "17/09/2025",
    "hora": "05:34 PM",
    "asunto": "TEXTO SUSTITUTORIO DE LOS PROYECTOS DE LEY 9143, 11002 Y 11046, QUE PROPONEN CREAR LA UNIVERSIDAD NACIONAL DE LENGUAS DEL VRAEM DE KIMBIRI (UNILEVRAEMKI) EN LA PROVINCIA DE LA CONVENCIÓN, DEPARTAMENTO DE CUSCO"
  },
  "004": {
    "tipo": "VOTACIÓN",
    "fecha": "17/09/2025",
    "hora": "05:39 PM",
    "asunto": "EXONERACIÓN DE LA SEGUNDA VOTACIÓN DEL TEXTO SUSTITUTORIO DE LOS PROYECTOS DE LEY 9143, 11002 Y 11046, QUE PROPONEN CREAR LA UNIVERSIDAD NACIONAL DE LENGUAS DEL VRAEM DE KIMBIRI (UNILEVRAEMKI) EN LA PROVINCIA DE LA CONVENCIÓN, DEPARTAMENTO DE CUSCO"
  },
  "006": {
    "tipo": "VOTACIÓN",
    "fecha": "17/09/2025",
    "hora": "05:47 PM",
    "asunto": "RATIFICACIÓN DEL ACUERDO DE LA JUNTA DE PORTAVOCES RESPECTO A LOS PROYECTOS DE LEY 9421, 11505 Y 11551, QUE PROPONEN CREAR LA UNIVERSIDAD NACIONAL DE CIENCIA, TECNOLOGÍA, HUMANIDADES Y AFINES DE HUAYCÁN, DISTRITO DE ATE VITARTE, PROVINCIA DE LIMA, DEPARTAMENTO DE LIMA"
  },
  "008": {
    "tipo": "VOTACIÓN",
    "fecha": "17/09/2025",
    "hora": "06:32 PM",
    "asunto": "TEXTO SUSTITUTORIO DE LOS PROYECTOS DE LEY 9421, 11505 Y 11551, QUE PROPONEN CREAR LA UNIVERSIDAD NACIONAL DE CIENCIA, TECNOLOGÍA, HUMANIDADES Y AFINES DE HUAYCÁN, DISTRITO DE ATE VITARTE, PROVINCIA DE LIMA, DEPARTAMENTO DE LIMA"
  },
  "009": {
    "tipo": "VOTACIÓN",
    "fecha": "17/09/2025",
    "hora": "06:36 PM",
    "asunto": "EXONERACIÓN DE LA SEGUNDA VOTACIÓN DEL TEXTO SUSTITUTORIO DE LOS PROYECTOS DE LEY 9421, 11505 Y 11551, QUE PROPONEN CREAR LA UNIVERSIDAD NACIONAL DE CIENCIA, TECNOLOGÍA, HUMANIDADES Y AFINES DE HUAYCÁN, DISTRITO DE ATE VITARTE, PROVINCIA DE LIMA, DEPARTAMENTO DE LIMA"
  },
  "011": {
    "tipo": "VOTACIÓN",
    "fecha": "17/09/2025",
    "hora": "06:58 PM",
    "asunto": "PROYECTO DE RESOLUCIÓN LEGISLATIVA 12439 QUE AUTORIZA A LA SEÑORA PRESIDENTA DE LA REPÚBLICA PARA SALIR DEL TERRITORIO NACIONAL DEL 21 AL 25 DE SETIEMBRE DE 2025, CON EL OBJETO DE VIAJAR A LA CIUDAD DE NUEVA YORK, ESTADOS UNIDOS DE AMÉRICA, A FIN DE PARTICIPAR EN LAS PRINCIPALES ACTIVIDADES DE LA SEMANA DE ALTO NIVEL DEL OCTOGÉSIMO PERIODO DE SESIONES DE LA ASAMBLEA GENERAL DE LAS NACIONES UNIDAS"
  },
  "013": {
    "tipo": "VOTACIÓN",
    "fecha": "17/09/2025",
    "hora": "07:34 PM",
    "asunto": "INSISTENCIA EN LA AUTÓGRAFA OBSERVADA POR LA PRESIDENCIA DE LA REPÚBLICA RECAÍDA EN LOS PROYECTOS DE LEY 3002, 3939, 4828, 5693, 6753, 7630, 7637, 7645, 7670, 7691, 7748, 7780, 7784, 7800, 7816, 7822, 7848, 7875, 7890, 7978, 7982, 8006, 8008, 8035, 8072, 8077, 8078, 8079, 8086, 8091, 8097, 8104, 8106, 8107, 8108, 8132 Y 8244, QUE PROPONEN CREAR UNIVERSIDADES NACIONALES EN LOS DEPARTAMENTOS DE AMAZONAS, APURÍMAC, AREQUIPA, AYACUCHO, CUSCO,"
  },
  "015": {
    "tipo": "VOTACIÓN",
    "fecha": "17/09/2025",
    "hora": "08:11 PM",
    "asunto": "TEXTO SUSTITUTORIO DEL PROYECTOS DE LEY 1358, 4559, 4868, 5404, 6712, 6716, 6821, 7004 Y 7186 QUE PROPONE MODIFICAR LA LEY 29701 -LEY QUE DISPONE BENEFICIOS A FAVOR DE LOS INTEGRANTES DE LAS JUNTAS VECINALES Y ESTABLECE EL DÍA DE LAS JUNTAS VECINALES DE SEGURIDAD CIUDADANA- PARA ESTABLECER MEDIDAS DE IDENTIFICACIÓN Y APOYO A LAS JUNTAS VECINALES DE SEGURIDAD CIUDADANA"
  },
  "016": {
    "tipo": "VOTACIÓN",
    "fecha": "17/09/2025",
    "hora": "08:16 PM",
    "asunto": "EXONERACIÓN DE LA SEGUNDA VOTACIÓN DEL TEXTO SUSTITUTORIO DEL PROYECTOS DE LEY 1358, 4559, 4868, 5404, 6712, 6716, 6821, 7004 Y 7186, QUE PROPONE MODIFICAR LA LEY 29701 -LEY QUE DISPONE BENEFICIOS A FAVOR DE LOS INTEGRANTES DE LAS JUNTAS VECINALES Y ESTABLECE EL DÍA DE LAS JUNTAS VECINALES DE SEGURIDAD CIUDADANA- PARA ESTABLECER MEDIDAS DE IDENTIFICACIÓN Y APOYO A LAS JUNTAS VECINALES DE SEGURIDAD CIUDADANA"
  },
  "018": {
    "tipo": "VOTACIÓN",
    "fecha": "17/09/2025",
    "hora": "08:46 PM",
    "asunto": "INSISTENCIA EN LA AUTÓGRAFA OBSERVADA POR LA PRESIDENCIA DE LA REPÚBLICA RECAÍDA EN EL PROYECTO DE LEY 11286, QUE PROPONE MODIFICAR EL DECRETO LEGISLATIVO 1666, DECRETO LEGISLATIVO MARCO DE LA GESTIÓN FISCAL DE LOS RECURSOS HUMANOS DEL SECTOR PÚBLICO"
  },
  "020": {
    "tipo": "VOTACIÓN",
    "fecha": "17/09/2025",
    "hora": "10:43 PM",
    "asunto": "TEXTO SUSTITUTORIO DE LOS PROYECTOS DE LEY 9002, 9003, 9024, 9103, 9499, 9571, 10153, 10170, 10227, 10355, 10440, 10483, 10493, 10614, 10620, 10684, 10698, 10782, 10989, 11165, 11169, 11202, 11265, 11274, 11331, 11385, 11416, 11439, 12417, 12450, 12460 Y 12461, QUE PROPONE AUTORIZAR EL RETIRO EXTRAORDINARIO Y FACULTATIVO DE LOS FONDOS DE LOS AFILIADOS AL SISTEMA PRIVADO DE PENSIONES HASTA POR EL MONTO DE CUATRO UNIDADES IMPOSITIVAS TRIBUTARIAS"
  },
  "021": {
    "tipo": "VOTACIÓN",
    "fecha": "17/09/2025",
    "hora": "10:46 PM",
    "asunto": "EXONERACIÓN DE LA SEGUNDA VOTACIÓN DEL TEXTO SUSTITUTORIO DE LOS PROYECTOS DE LEY 9002, 9003, 9024, 9103, 9499, 9571, 10153, 10170, 10227, 10355, 10440, 10483, 10493, 10614, 10620, 10684, 10698, 10782, 10989, 11165, 11169, 11202, 11265, 11274, 11331, 11385, 11416, 11439, 12417, 12450, 12460 Y 12461, QUE PROPONE AUTORIZAR EL RETIRO EXTRAORDINARIO Y FACULTATIVO DE LOS FONDOS DE LOS AFILIADOS AL SISTEMA PRIVADO DE PENSIONES HASTA POR EL MONTO DE"
  },
  "023": {
    "tipo": "VOTACIÓN",
    "fecha": "17/09/2025",
    "hora": "10:55 PM",
    "asunto": "RATIFICACIÓN DEL ACUERDO DE LA JUNTA DE PORTAVOCES QUE ACUERDA LA EXONERACIÓN DE DICTAMEN DE LA COMISIÓN DE SALUD RESPECTO DEL PROYECTO DE LEY 3473; LA EXONERACIÓN DE DICTAMEN DE LA COMISIÓN DE PRESUPUESTO SOBRE EL PROYECTO DE LEY 5003; LA EXONERACIÓN DE DICTAMEN DE LA COMISIÓN DE DESCENTRALIZACIÓN RESPECTO DE LOS PROYECTOS DE LEY 6761, 7234, 7326, 7484 Y 7657; LA EXONERACIÓN DE DICTAMEN DE LA COMISIÓN DE TRABAJO SOBRE LOS PROYECTOS DE LEY 8861"
  },
  "025": {
    "tipo": "VOTACIÓN",
    "fecha": "17/09/2025",
    "hora": "11:52 PM",
    "asunto": "TEXTO SUSTITUTORIO DE LOS PROYECTOS DE LEY 1901, 2290, 3117, 3473, 5003, 6234, 6368, 6761, 6895, 7234, 7326, 7484, 7657, 8861, 9841 Y 11058, QUE PROPONE HACER EXTENSIVO A LOS SERVIDORES Y FUNCIONARIOS PÚBLICOS EL DERECHO A PERCIBIR GRATIFICACIONES DE FIESTAS PATRIAS Y DE NAVIDAD"
  },
  "027": {
    "tipo": "VOTACIÓN",
    "fecha": "18/09/2025",
    "hora": "00:10 AM",
    "asunto": "CUESTIÓN PREVIA PARA QUE RETORNE A LA COMISIÓN DE TRABAJO EL PROYECTO DE LEY 9142, QUE PROPONE DECLARAR DE INTERÉS NACIONAL LA CESIÓN EN USO DE CINCO HECTÁREAS DEL FUNDO EL PORVENIR UBICADO EN EL DISTRITO EL TAMBO, PROVINCIA HUANCAYO, DEPARTAMENTO JUNÍN, PARA LA AMPLIACIÓN DE LA INFRAESTRUCTURA EDUCATIVA DE LA UNIVERSIDAD NACIONAL DEL CENTRO DEL PERÚ"
  }
}