{
  "003": {
    "tipo": "VOTACIÓN",
    "fecha": "14/06/2011",
    "hora": "05:47 PM",
    "asunto": "PROY 4590, LEY QUE AUTORIZA LA CONCLUSIÓN DEL NOMBRAMIENTO DEL PERSONAL CONTRATADO DEL SECTOR PÚBLICO Y PRECISA LOS ALCANCES DE LOS LINEAMIENTOS ESTABLECIDOS EN EL DECRETO SUPREMO 111-2010-PCM"
  },
  "004": {
    "tipo": "VOTACIÓN",
    "fecha": "14/06/2011",
    "hora": "05:54 PM",
    "asunto": "EXONERACIÓN DE 2DA VOTACIÓN DEL PROY 4590, LEY QUE AUTORIZA LA CONCLUSIÓN DEL NOMBRAMIENTO DEL PERSONAL CONTRATADO DEL SECTOR PÚBLICO Y PRECISA LOS ALCANCES DE LOS LINEAMIENTOS ESTABLECIDOS EN EL DECRETO SUPREMO 111-2010-PCM"
  },
  "006": {
    "tipo": "VOTACION",
    "fecha": "14/06/2011",
    "hora": "06:08 PM",
    "asunto": "RECONSIDERACIÓN DEL PROY 3870, LEY QUE INCORPORA EL ARTÍCULO 4-A A LA LEY 28424, LEY QUE CREA EL IMPUESTO TEMPORAL A LOS ACTIVOS NETOS, RESPECTO DE LAS COOPERATIVAS"
  },
  "008": {
    "tipo": "VOTACIÓN",
    "fecha": "14/06/2011",
    "hora": "06:25 PM",
    "asunto": "INSISTENCIA DEL PROY 3870, LEY QUE INCORPORA EL ARTÍCULO 4-A A LA LEY 28424, LEY QUE CREA EL IMPUESTO TEMPORAL A LOS ACTIVOS NETOS, RESPECTO DE LAS COOPERATIVAS"
  },
  "010": {
    "tipo": "VOTACIÓN",
    "fecha": "14/06/2011",
    "hora": "07:06 PM",
    "asunto": "INSISTENCIA DE LOS PROYS 221 Y 806, LEY QUE REGULA EL USO, PRESERVACIÓN, DESARROLLO, RECUPERACIÓN, FOMENTO Y DIFUSIÓN DE LAS LENGUAS ORIGINARIAS DEL PERÚ"
  },
  "012": {
    "tipo": "VOTACION",
    "fecha": "14/06/2011",
    "hora": "07:13 PM",
    "asunto": "PROY 3562, LEY QUE DECLARA LA INTANGIBILIDAD DE LA LAGUNA DE LA HUACACHINA"
  },
  "013": {
    "tipo": "VOTACIÓN",
    "fecha": "14/06/2011",
    "hora": "07:19 PM",
    "asunto": "EXONERACIÓN DE 2DA VOTACIÓN DEL PROY 3562, LEY QUE DECLARA LA INTANGIBILIDAD DE LA LAGUNA DE LA HUACACHINA"
  },
  "015": {
    "tipo": "VOTACIÓN",
    "fecha": "14/06/2011",
    "hora": "07:34 PM",
    "asunto": "INSISTENCIA DEL PROY 3214, LEY QUE DEROGA LOS DECRETOS LEGISLATIVOS 977 Y 978 Y RESTITUYE LA PLENA VIGENCIA DE LA LEY 27037, LEY DE PROMOCIÓN DE LA INVERSIÓN EN LA AMAZONÍA"
  },
  "017": {
    "tipo": "VOTACIÓN",
    "fecha": "14/06/2011",
    "hora": "08:15 PM",
    "asunto": "INSISTENCIA, PROY 4100, MODIFICACION DEL ART 4 DE LA LEY 28212, LEY QUE REGULA LOS INGRESOS DE LOS ALTOS FUNCIONARIOS, AUTORIDADES DEL ESTADO Y DICTA OTRAS MEDIDAS"
  }
}