{
  "003": {
    "tipo": "VOTACIÓN",
    "fecha": "30/10/2024",
    "hora": "03:37 PM",
    "asunto": "PROYECTO DE LEY 8628, QUE PROPONE LA NO APROBACIÓN DE LA CUENTA GENERAL DE LA REPÚBLICA CORRESPONDIENTE AL EJERCICIO FISCAL 2023"
  },
  "005": {
    "tipo": "VOTACIÓN",
    "fecha": "30/10/2024",
    "hora": "03:45 PM",
    "asunto": "PROYECTO DE RESOLUCIÓN LEGISLATIVA DEL CONGRESO 9338. PROYECTO DE AGENDA LEGISLATIVA ELABORADO CON LOS GRUPOS PARLAMENTARIOS, LAS 24 COMISIONES ORDINARIAS Y LA PRESIDENCIA DEL CONSEJO DE MINISTROS"
  }
}