{
  "003": {
    "tipo": "VOTACIÓN",
    "fecha": "01/09/2016",
    "hora": "09:42 AM",
    "asunto": "CONFORMACIÓN DE LA COMISIÓN DE ÉTICA PARLAMENTARIA PARA EL PERÍODO 2016 - 2018"
  },
  "005": {
    "tipo": "VOTACIÓN",
    "fecha": "01/09/2016",
    "hora": "09:51 AM",
    "asunto": "CONFORMACIÓN DE LA COMISIÓN DE LEVANTAMIENTO DE INMUNIDAD PARLAMENTARIA PARA EL PERÍODO 2016 - 2017"
  },
  "007": {
    "tipo": "VOTACIÓN",
    "fecha": "01/09/2016",
    "hora": "10:11 AM",
    "asunto": "MOCIÓN 182 (ADMISIÓN); OTORGA FACULTADES DE COMISIÓN INVESTIGADORA A LA COMISIÓN DE FISCALIZACIÓN Y CONTRALORÍA, CONFORME AL ARTÍCULO 88 DEL REGLAMENTO DEL CONGRESO DE LA REPÚBLICA, HASTA POR 180 DÍAS HÁBILES"
  },
  "009": {
    "tipo": "VOTACIÓN",
    "fecha": "01/09/2016",
    "hora": "12:04 PM",
    "asunto": "MOCIÓN 182; OTORGA FACULTADES DE COMISIÓN INVESTIGADORA A LA COMISIÓN DE FISCALIZACIÓN, HASTA POR 180 DÍAS HÁBILES, PARA INVESTIGAR LA PRESUNTA INTROMISIÓN, ACTOS Y HECHOS EN LOS QUE PODRÍA HABER INCURRIDO LA SEÑORA NADINE HEREDIA ALARCÓN, QUE CONFIGURARÍAN EL PRESUNTO DELITO DE USURPACIÓN DE FUNCIONES Y OTROS PRESUNTOS DELITOS, ASÍ TAMBIÉN, CONTRA LAS PERSONAS QUE PUDIERAN RESULTAR RESPONSABLES, DURANTE EL PERÍODO PRESIDENCIAL 2011 - 2016"
  }
}